{
    "name": "Usuario",
    "fields": [
        {
            "fieldName": "username",
            "fieldType": "String",
            "fieldValidateRules": [
                "required"
            ]
        },
        {
            "fieldName": "email",
            "fieldType": "String",
            "fieldValidateRules": [
                "required"
            ]
        },
        {
            "fieldName": "password",
            "fieldType": "String",
            "fieldValidateRules": [
                "required"
            ]
        },
        {
            "fieldName": "enable",
            "fieldType": "Boolean"
        }
    ],
    "relationships": [
        {
            "relationshipType": "one-to-many",
            "otherEntityName": "contact",
            "otherEntityRelationshipName": "username",
            "relationshipName": "name"
        }
    ],
    "changelogDate": "20200226124000",
    "entityTableName": "usuario",
    "dto": "mapstruct",
    "pagination": "pagination",
    "service": "serviceImpl",
    "jpaMetamodelFiltering": false,
    "fluentMethods": true,
    "readOnly": false,
    "clientRootFolder": "agenda",
    "applications": "*",
    "microserviceName": "agenda"
}